{"web":{"client_id":"879384897975-dc1635p3aq73poiks8u78f7h2prv8tt6.apps.googleusercontent.com","project_id":"restaurant-menu-app-152704","auth_uri":"https://accounts.google.com/o/oauth2/auth","token_uri":"https://accounts.google.com/o/oauth2/token","auth_provider_x509_cert_url":"https://www.googleapis.com/oauth2/v1/certs","client_secret":"7rGuPdS7StQUqE77KtKf4QDB","redirect_uris":["http://localhost:8000/login","http://localhost:8000/gconnect","https://localhost:8000/oauth2callback"],"javascript_origins":["http://localhost:5000","http://localhost:8000"]}}